harvesters/__init__.py
harvesters/_version.py
harvesters/core.py
harvesters/_private/__init__.py
harvesters/_private/core/__init__.py
harvesters/_private/core/command.py
harvesters/_private/core/observer.py
harvesters/_private/core/port.py
harvesters/_private/core/statistics.py
harvesters/_private/core/subject.py
harvesters/_private/core/helper/__init__.py
harvesters/_private/core/helper/profiler.py
harvesters/_private/core/helper/system.py
harvesters/logging/logging.ini
harvesters/logging/logging.report.ini
harvesters/test/__init__.py
harvesters/test/base_harvester.py
harvesters/test/helper.py
harvesters/test/test_245.py
harvesters/test/test_319.py
harvesters/test/test_321.py
harvesters/test/test_345.py
harvesters/test/test_351.py
harvesters/test/test_acq_frame_rate.py
harvesters/test/test_deprecated_items.py
harvesters/test/test_harvester_core.py
harvesters/test/test_performance.py
harvesters/test/test_tutorials.py
harvesters/test/xml/issue_66_altered_plain.xml
harvesters/test/xml/issue_66_altered_zip.zip
harvesters/test/xml/issue_67_altered_plain.xml
harvesters/test/xml/issue_67_altered_zip.zip
harvesters/util/__init__.py
harvesters/util/_pfnc.py
harvesters/util/logging.py
harvesters/util/pfnc.py
harvesters-1.4.3.dist-info/LICENSE.txt
harvesters-1.4.3.dist-info/METADATA
harvesters-1.4.3.dist-info/WHEEL
harvesters-1.4.3.dist-info/top_level.txt
harvesters-1.4.3.dist-info/RECORD
