Metadata-Version: 2.1
Name: harvesters
Version: 1.4.3
Summary: Image Acquisition Library for GenICam-based Machine Vision System
Home-page: https://github.com/genicam/harvesters
Download-URL: https://pypi.org/project/harvesters/
Author: The GenICam Committee
Author-email: genicam@list.stemmer-imaging.com
License: Apache Software License V2.0
Platform: any
Classifier: Development Status :: 5 - Production/Stable
Classifier: Intended Audience :: Science/Research
Classifier: Intended Audience :: Education
Classifier: Intended Audience :: Developers
Classifier: License :: OSI Approved :: Apache Software License
Classifier: Operating System :: MacOS :: MacOS X
Classifier: Operating System :: Microsoft :: Windows
Classifier: Operating System :: POSIX
Provides: harvesters
License-File: LICENSE.txt
